purrsong/__init__.py
purrsong/api.py
purrsong/apps/__init__.py
purrsong/apps/catface.py
purrsong/datasets/__init__.py
purrsong/datasets/cats.py
purrsong/datasets/core.py
purrsong/models/__init__.py
purrsong/models/core.py
purrsong/utils/__init__.py
purrsong/utils/downloader.py
purrsong/utils/extractor.py
purrsong/utils/path.py
purrsong-0.1.9.dist-info/LICENSE
purrsong-0.1.9.dist-info/METADATA
purrsong-0.1.9.dist-info/WHEEL
purrsong-0.1.9.dist-info/top_level.txt
purrsong-0.1.9.dist-info/RECORD
