Metadata-Version: 2.1
Name: purrsong
Version: 0.1.9
Summary: purrsong
Home-page: https://github.com/jeakwon/purrsong
Author: jeakwon
Author-email: onlytojay@gmail.com
License: LICENSE.txt
Keywords: purrsong
Platform: UNKNOWN
Requires-Python: >=3.6
